README.md
setup.py
tornado_models/__init__.py
tornado_models/base.py
tornado_models/redis.py
tornado_models/sqlalchemy.py
tornado_models.egg-info/PKG-INFO
tornado_models.egg-info/SOURCES.txt
tornado_models.egg-info/dependency_links.txt
tornado_models.egg-info/requires.txt
tornado_models.egg-info/top_level.txt