Metadata-Version: 2.1
Name: tornado-models
Version: 0.0.7
Summary: sqlalchemy and redis for tornado
Home-page: https://github.com/BSTester/tornado-models
Author: 贝克街的捉虫师
Author-email: forpeng@foxmail.com
License: Apache License 2.0
Platform: UNKNOWN
Classifier: Environment :: Console
Classifier: Intended Audience :: Developers
Classifier: Natural Language :: Chinese (Simplified)
Classifier: Operating System :: OS Independent
Classifier: Programming Language :: Python :: 3.7
Classifier: Programming Language :: Python :: 3.8
Classifier: Programming Language :: Python :: 3 :: Only
